pyramid_errbit/__init__.py
pyramid_errbit/_version.py
pyramid_errbit-0.0.7.dist-info/DESCRIPTION.rst
pyramid_errbit-0.0.7.dist-info/METADATA
pyramid_errbit-0.0.7.dist-info/metadata.json
pyramid_errbit-0.0.7.dist-info/RECORD
pyramid_errbit-0.0.7.dist-info/top_level.txt
pyramid_errbit-0.0.7.dist-info/WHEEL
