Metadata-Version: 2.0
Name: pyramid-errbit
Version: 0.0.7
Summary: Bindings for the pyramid webframework and the errbit reporting system.
Home-page: https://github.com/bitesofcode/pyramid_errbit
Author: Eric Hulser
Author-email: eric.hulser@gmail.com
License: MIT
Platform: UNKNOWN
